.DS_Store
class_functions/__init__.py
class_functions/main.py
class_functions-0.2.10.dist-info/METADATA
class_functions-0.2.10.dist-info/WHEEL
class_functions-0.2.10.dist-info/top_level.txt
class_functions-0.2.10.dist-info/RECORD
