Metadata-Version: 2.4
Name: class_functions
Version: 0.2.10
Summary: A package of functions for use in creating educational material.
Author: R. N. Guymon
Author-email: rnguymon@illinois.edu
Requires-Dist: pandas
Requires-Dist: matplotlib
Requires-Dist: seaborn
Requires-Dist: plotly-express
Requires-Dist: numpy
Requires-Dist: IPython
Requires-Dist: nbformat
Requires-Dist: python-docx
Requires-Dist: pygments
Dynamic: author
Dynamic: author-email
Dynamic: description
Dynamic: description-content-type
Dynamic: requires-dist
Dynamic: summary
